{"frames": {

"bg_wakaland_1.png":
{
	"frame": {"x":0,"y":0,"w":256,"h":224},
	"rotated": false,
	"trimmed": false,
	"spriteSourceSize": {"x":0,"y":0,"w":256,"h":224},
	"sourceSize": {"w":256,"h":224}
},
"bg_wakaland_2.png":
{
	"frame": {"x":0,"y":224,"w":256,"h":224},
	"rotated": false,
	"trimmed": false,
	"spriteSourceSize": {"x":0,"y":0,"w":256,"h":224},
	"sourceSize": {"w":256,"h":224}
},
"bg_wakaland_3.png":
{
	"frame": {"x":0,"y":448,"w":256,"h":224},
	"rotated": false,
	"trimmed": false,
	"spriteSourceSize": {"x":0,"y":0,"w":256,"h":224},
	"sourceSize": {"w":256,"h":224}
},
"block.png":
{
	"frame": {"x":0,"y":672,"w":16,"h":16},
	"rotated": false,
	"trimmed": false,
	"spriteSourceSize": {"x":0,"y":0,"w":16,"h":16},
	"sourceSize": {"w":16,"h":16}
},
"coin1.png":
{
	"frame": {"x":16,"y":672,"w":16,"h":16},
	"rotated": false,
	"trimmed": false,
	"spriteSourceSize": {"x":0,"y":0,"w":16,"h":16},
	"sourceSize": {"w":16,"h":16}
},
"coin2.png":
{
	"frame": {"x":32,"y":672,"w":16,"h":16},
	"rotated": false,
	"trimmed": false,
	"spriteSourceSize": {"x":0,"y":0,"w":16,"h":16},
	"sourceSize": {"w":16,"h":16}
},
"coin3.png":
{
	"frame": {"x":48,"y":672,"w":16,"h":16},
	"rotated": false,
	"trimmed": false,
	"spriteSourceSize": {"x":0,"y":0,"w":16,"h":16},
	"sourceSize": {"w":16,"h":16}
},
"coin4.png":
{
	"frame": {"x":64,"y":672,"w":15,"h":16},
	"rotated": false,
	"trimmed": false,
	"spriteSourceSize": {"x":0,"y":0,"w":15,"h":16},
	"sourceSize": {"w":15,"h":16}
},
"rat_back.png":
{
	"frame": {"x":79,"y":672,"w":32,"h":32},
	"rotated": false,
	"trimmed": false,
	"spriteSourceSize": {"x":0,"y":0,"w":32,"h":32},
	"sourceSize": {"w":32,"h":32}
},
"rat_blink.png":
{
	"frame": {"x":111,"y":672,"w":32,"h":32},
	"rotated": false,
	"trimmed": false,
	"spriteSourceSize": {"x":0,"y":0,"w":32,"h":32},
	"sourceSize": {"w":32,"h":32}
},
"rat_idle.png":
{
	"frame": {"x":143,"y":672,"w":32,"h":32},
	"rotated": false,
	"trimmed": false,
	"spriteSourceSize": {"x":0,"y":0,"w":32,"h":32},
	"sourceSize": {"w":32,"h":32}
},
"rat_jump.png":
{
	"frame": {"x":175,"y":672,"w":32,"h":32},
	"rotated": false,
	"trimmed": false,
	"spriteSourceSize": {"x":0,"y":0,"w":32,"h":32},
	"sourceSize": {"w":32,"h":32}
},
"rat_run.png":
{
	"frame": {"x":207,"y":672,"w":32,"h":32},
	"rotated": false,
	"trimmed": false,
	"spriteSourceSize": {"x":0,"y":0,"w":32,"h":32},
	"sourceSize": {"w":32,"h":32}
},
"rat_walk.png":
{
	"frame": {"x":0,"y":704,"w":32,"h":32},
	"rotated": false,
	"trimmed": false,
	"spriteSourceSize": {"x":0,"y":0,"w":32,"h":32},
	"sourceSize": {"w":32,"h":32}
}},
"animations": {
	"bg_wakaland": ["bg_wakaland_1.png","bg_wakaland_2.png","bg_wakaland_3.png"],
	"coin": ["coin1.png","coin2.png","coin3.png","coin4.png"]
},
"meta": {
	"app": "https://www.codeandweb.com/texturepacker",
	"version": "1.0",
	"image": "rat.png",
	"format": "RGBA8888",
	"size": {"w":256,"h":736},
	"scale": "1",
	"smartupdate": "$TexturePacker:SmartUpdate:6ae783e63785d2c768c0f8996c295dd3:f628a070fc61ed56f3f8200d0be88f98:897eb3d5a631cb8958a6b43d97451b25$"
}
}
